RTL/dmem.v
module dmem#(parameter depth=256)(
    input clk,
    input we,
    input [31:0]addr,
    input [31:0]wdata,
    input [2:0]funct3,
    output reg [31:0]rdata
);

reg [7:0] mem[0:(depth*4)-1];

always @(posedge clk)
begin
    if (we)begin
        case(funct3)
        3'b000:begin
            mem[addr]<=wdata[7:0];
        end
        3'b001:begin
            mem[addr]<=wdata[7:0];
            mem[addr+1]<=wdata[15:8];
        end
        3'b010:begin
            mem[addr]<=wdata[7:0];
            mem[addr+1]<=wdata[15:8];
            mem[addr+2]<=wdata[23:16];
            mem[addr+3]<=wdata[31:24];
        end
        default: ;
        endcase
    end
end
always @(*)
begin
    case(funct3)
    3'b000:begin
        rdata={{24{mem[addr][7]}},mem[addr]};
    end
    3'b001:begin
        rdata={{16{mem[addr+1][7]}},mem[addr+1],mem[addr]};
    end
    3'b010:begin
        rdata={mem[addr+3],mem[addr+2],mem[addr+1],mem[addr]};
    end
    3'b100:begin
        rdata={24'b0,mem[addr]};
    end
    3'b101:begin
        rdata={16'b0,mem[addr+1],mem[addr]};
    end
    default:rdata=32'b0;
    endcase
end
endmodule

alu.v
module alu (
    input  [31:0] a,
    input  [31:0] b,
    input  [3:0] aluop,
    output reg [31:0] result,
    output wire zero
);
wire [4:0]shiftamt =b[4:0];

always@(*)begin
    case (aluop)
    4'b0000: result =a+b;
    4'b0001: result =a-b;
    4'b0010: result =a&b;
    4'b0011: result =a|b;
    4'b0100: result =a^b;
    4'b0101: result =($signed(a)<$signed(b))?32'd1:32'd0;
    4'b0110: result =(a<b);
    4'b0111: result =a<<shiftamt;
    4'b1000: result =a>>shiftamt;
    4'b1001: result =$signed(a)>>>shiftamt;
    default: result= 32'b0;
    endcase
end

assign zero =(result==32'd0);
endmodule

RTL/immgen.v
module immgen(
    input [31:0] instr,
    input [2:0] imm_sel,
    output reg [31:0] immediate
);

always @(*) begin
    case (imm_sel)
       3'b000: immediate= {{20{instr[31]}},instr[31:20]};
       3'b001: immediate= {{20{instr[31]}},instr[31:25],instr[11:7]};
       3'b010: immediate= {{19{instr[31]}}, instr[31], instr[7],instr[30:25], instr[11:8], 1'b0};
       3'b011: immediate = {instr[31:12], 12'b0};
       3'b100: immediate = {{11{instr[31]}}, instr[31], instr[19:12],instr[20], instr[30:21], 1'b0};
    endcase
end
endmodule

RTL/regfile.v
module regfile(
    input clk,
    input wen,
    input [4:0] waddr,
    input [31:0] wdata,
    input [4:0] raddr1,
    input [4:0] raddr2,
    output [31:0] rdata1,
    output [31:0] rdata2
);
reg [31:0] regs[0:31];
integer i;
 initial for(i=0;i<32;i++) regs[i]=32'b0;

always @(posedge clk)
if (wen && waddr !=5'b0) regs[waddr]<= wdata;

assign rdata1= (raddr1==0)? 32'b0 : regs[raddr1];
assign rdata2= (raddr2==0)? 32'b0 : regs[raddr2];
endmodule

RTL/control.v
module control(
    input  [6:0]opcode,
    input  [2:0]funct3,
    input  [6:0]funct7,
    output reg reg_write,
    output reg alu_src,
    output reg mem_read,
    output reg mem_write,
    output reg branch,
    output reg jump,
    output reg [1:0]wb_sel,
    output reg [3:0]alu_op,
    output reg [2:0]imm_sel
);

localparam R = 7'b0110011;
localparam I = 7'b0010011;
localparam LOAD = 7'b0000011;
localparam STORE = 7'b0100011;
localparam BR = 7'b1100011;
localparam JAL = 7'b1101111;
localparam JALR= 7'b1100111;  
localparam LUI = 7'b0110111;  
localparam AUIP= 7'b0010111;  


always @(*) begin
    {reg_write,alu_src,mem_read,mem_write,branch,jump}=6'b0;
    wb_sel=2'b00; alu_op=4'b0000; imm_sel=3'b000;
    //safe assignment
    case (opcode)
        R: begin
            reg_write=1; alu_src=0; wb_sel=2'b00;
            case({funct7[5],funct3})
                4'b0000: alu_op=4'b0000; // ADD
                4'b1000: alu_op=4'b0001; // SUB
                4'b0111: alu_op=4'b0010; // AND
                4'b0110: alu_op=4'b0011; // OR
                4'b0100: alu_op=4'b0100; // XOR
                4'b0010: alu_op=4'b0101; // SLT
                4'b0011: alu_op=4'b0110; // SLTU
                4'b0001: alu_op=4'b0111; // SLL
                4'b0101: alu_op=4'b1000; // SRL
                4'b1101: alu_op=4'b1001; // SRA
                default: alu_op=4'b0000;
            endcase
        end

        I:  begin 
            reg_write=1; alu_src=1; wb_sel=2'b00; imm_sel=3'b000;
            case(funct3)
                3'h0: alu_op=4'b0000; // ADDI
                3'h7: alu_op=4'b0010; // ANDI
                3'h6: alu_op=4'b0011; // ORI
                3'h4: alu_op=4'b0100; // XORI
                3'h2: alu_op=4'b0101; // SLTI
                3'h3: alu_op=4'b0110; // SLTIU
                3'h1: alu_op=4'b0111; // SLLI
                3'h5: alu_op=(funct7[5])?4'b1001:4'b1000; // SRAI/SRLI
                default: alu_op=4'b0000;
            endcase
        end

        LOAD: begin 
            reg_write=1; alu_src=1; mem_read=1; wb_sel=2'b01; imm_sel=3'b000; alu_op=4'b0000;
        end

        STORE: begin 
            alu_src=1; mem_write=1; imm_sel=3'b001; alu_op=4'b0000;
        end

        BR: begin
            branch = 1; alu_src = 0; imm_sel = 3'b010; alu_op = 4'b0001; 
end
        JAL:  begin 
            reg_write=1; jump=1; wb_sel=2'b10; imm_sel=3'b100;
        end
            
        JALR: begin 
                reg_write=1; alu_src=1; jump=1; wb_sel=2'b10; imm_sel=3'b000; alu_op=4'b0000; 
        end
                
        LUI:  begin
                 reg_write=1; wb_sel=2'b11; imm_sel=3'b011; 
        end
                 
        AUIP: begin
                 reg_write=1; alu_src=1; wb_sel=2'b00; imm_sel=3'b011; alu_op=4'b0000; 
        end

        default: ;
    endcase
end
endmodule

RTL/imem.v
module imem #(parameter depth = 256)(addr,instr);
input [31:0]addr;
output [31:0] instr;
reg [31:0] mem[0:depth-1];
initial $readmemh("program1.hex",mem);
assign instr=mem[addr[31:2]];
endmodule

pc.v
module program_counter(clk,rst,pc_next,pc);
input clk,rst;
input wire [31:0]pc_next;
output reg [31:0]pc;
always @(posedge clk) begin
    if (rst) pc=32'h00000000;
    else pc<=pc_next;
end
endmodule

RTL/instfetch.v
module instfetch(clk,rst,pc_next,pc,instr);
input clk,rst;
input [31:0]pc_next;
output [31:0]instr;
output [31:0] pc;//only for tb purpose this is output,otherwire internally used by imem 
program_counter pcconnect(clk,rst,pc_next,pc);
imem imemconnect(pc,instr);
endmodule

RTL/rilscore.v
module RILS_core(
    input clk,rst
);
wire [31:0] pc, pc_next, instr;
assign pc_next=pc+32'd4;
instfetch if0(clk,rst,pc_next,pc,instr);

//decoding
wire[6:0] opcode =instr[6:0];
wire [4:0] rd =instr[11:7];
wire [2:0] funct3 =instr[14:12];
wire [4:0] rs1 = instr[19:15];
wire [4:0] rs2= instr[24:20];
wire [6:0] funct7=instr[31:25];

//control unit
wire reg_write, alu_src;
wire [3:0] alu_op;
wire [2:0] imm_sel;
wire mem_read, mem_write, branch, jump;
wire [1:0] wb_sel;
control ctrl(
    .opcode(opcode),
    .funct3(funct3),
    .funct7(funct7),
    .reg_write(reg_write),
    .alu_src(alu_src),
    .mem_read(mem_read),
    .mem_write(mem_write),
    .branch(branch),
    .jump(jump),
    .wb_sel(wb_sel),
    .alu_op(alu_op),
    .imm_sel(imm_sel)
);

//regfile
wire [31:0] rdata1,rdata2,wb_data;
regfile rf (
    .clk(clk),
    .wen(reg_write),
    .waddr(rd),
    .wdata(wb_data),
    .raddr1(rs1),
    .raddr2(rs2),
    .rdata1(rdata1),
    .rdata2(rdata2)
);

//immediate gen
wire [31:0] imm;
immgen ig0(
    .instr(instr),
    .imm_sel(imm_sel),
    .immediate(imm)
);

//ALU source mux
wire [31:0] alu_b   = alu_src ? imm : rdata2;
wire [31:0]alu_result;
wire zero;
alu alu0(
    .a(rdata1),
    .b(alu_b),
    .aluop(alu_op),
    .result(alu_result),
    .zero(zero)
);

//Data Memory
wire [31:0]dmem_rdata;
dmem dmem0(
    .clk(clk),
    .we(mem_write),
    .addr(alu_result),
    .wdata(rdata2),
    .funct3(funct3),
    .rdata(dmem_rdata)
);

//write back from alu/ data mem
assign wb_data=wb_sel?dmem_rdata:alu_result;
endmodule

RTL/rilscoretb.v
// tb_core_rim.v — Testbench for core_rils (loads + stores)
// Program: addi x1,x0,42  → sw x1,0(x0)  → lw x2,0(x0)
// Expected: x2 == 42 after lw executes
`timescale 1ns/1ps
module tb_core_rils;
    reg clk = 0, rst = 1;
    always #5 clk = ~clk;

    RILS_core dut (.clk(clk), .rst(rst));

   initial begin
        
        $dumpfile("tb_core_rils.vcd");
        $dumpvars(0, tb_core_rils);

        #10;
        rst = 0;

        repeat(6) @(posedge clk); // run 6 cycles
        #1;

        // Inspect x2
        if (dut.rf.regs[2] === 32'd42)
            $display("PASS: x2 = %0d (expected 42)", dut.rf.regs[2]);
        else
            $display("FAIL: x2 = %0d (expected 42)", dut.rf.regs[2]);

        $finish;
    end
endmodule

VCD/tb_core_rils.vcd
$date
	Thu Aug 13 01:26:31 2026
$end
$version
	Icarus Verilog
$end
$timescale
	1ps
$end
$scope module tb_core_rils $end
$var reg 1 ! clk $end
$var reg 1 " rst $end
$scope module dut $end
$var wire 1 ! clk $end
$var wire 1 " rst $end
$var wire 1 # zero $end
$var wire 2 $ wb_sel [1:0] $end
$var wire 32 % wb_data [31:0] $end
$var wire 5 & rs2 [4:0] $end
$var wire 5 ' rs1 [4:0] $end
$var wire 1 ( reg_write $end
$var wire 32 ) rdata2 [31:0] $end
$var wire 32 * rdata1 [31:0] $end
$var wire 5 + rd [4:0] $end
$var wire 32 , pc_next [31:0] $end
$var wire 32 - pc [31:0] $end
$var wire 7 . opcode [6:0] $end
$var wire 1 / mem_write $end
$var wire 1 0 mem_read $end
$var wire 1 1 jump $end
$var wire 32 2 instr [31:0] $end
$var wire 3 3 imm_sel [2:0] $end
$var wire 32 4 imm [31:0] $end
$var wire 7 5 funct7 [6:0] $end
$var wire 3 6 funct3 [2:0] $end
$var wire 32 7 dmem_rdata [31:0] $end
$var wire 1 8 branch $end
$var wire 1 9 alu_src $end
$var wire 32 : alu_result [31:0] $end
$var wire 4 ; alu_op [3:0] $end
$var wire 32 < alu_b [31:0] $end
$scope module alu0 $end
$var wire 32 = b [31:0] $end
$var wire 1 # zero $end
$var wire 5 > shiftamt [4:0] $end
$var wire 4 ? aluop [3:0] $end
$var wire 32 @ a [31:0] $end
$var reg 32 A result [31:0] $end
$upscope $end
$scope module ctrl $end
$var wire 3 B funct3 [2:0] $end
$var wire 7 C funct7 [6:0] $end
$var wire 7 D opcode [6:0] $end
$var parameter 7 E AUIP $end
$var parameter 7 F BR $end
$var parameter 7 G I $end
$var parameter 7 H JAL $end
$var parameter 7 I JALR $end
$var parameter 7 J LOAD $end
$var parameter 7 K LUI $end
$var parameter 7 L R $end
$var parameter 7 M STORE $end
$var reg 4 N alu_op [3:0] $end
$var reg 1 9 alu_src $end
$var reg 1 8 branch $end
$var reg 3 O imm_sel [2:0] $end
$var reg 1 1 jump $end
$var reg 1 0 mem_read $end
$var reg 1 / mem_write $end
$var reg 1 ( reg_write $end
$var reg 2 P wb_sel [1:0] $end
$upscope $end
$scope module dmem0 $end
$var wire 32 Q addr [31:0] $end
$var wire 1 ! clk $end
$var wire 3 R funct3 [2:0] $end
$var wire 1 / we $end
$var wire 32 S wdata [31:0] $end
$var parameter 32 T depth $end
$var reg 32 U rdata [31:0] $end
$upscope $end
$scope module if0 $end
$var wire 1 ! clk $end
$var wire 32 V pc_next [31:0] $end
$var wire 1 " rst $end
$var wire 32 W pc [31:0] $end
$var wire 32 X instr [31:0] $end
$scope module imemconnect $end
$var wire 32 Y instr [31:0] $end
$var wire 32 Z addr [31:0] $end
$var parameter 32 [ depth $end
$upscope $end
$scope module pcconnect $end
$var wire 1 ! clk $end
$var wire 32 \ pc_next [31:0] $end
$var wire 1 " rst $end
$var reg 32 ] pc [31:0] $end
$upscope $end
$upscope $end
$scope module ig0 $end
$var wire 3 ^ imm_sel [2:0] $end
$var wire 32 _ instr [31:0] $end
$var reg 32 ` immediate [31:0] $end
$upscope $end
$scope module rf $end
$var wire 1 ! clk $end
$var wire 5 a raddr1 [4:0] $end
$var wire 5 b raddr2 [4:0] $end
$var wire 5 c waddr [4:0] $end
$var wire 32 d wdata [31:0] $end
$var wire 1 ( wen $end
$var wire 32 e rdata2 [31:0] $end
$var wire 32 f rdata1 [31:0] $end
$var integer 32 g i [31:0] $end
$upscope $end
$upscope $end
$upscope $end
$enddefinitions $end
$comment Show the parameter values. $end
$dumpall
b100000000 [
b100000000 T
b100011 M
b110011 L
b110111 K
b11 J
b1100111 I
b1101111 H
b10011 G
b1100011 F
b10111 E
$end
#0
$dumpvars
b100000 g
bx f
bx e
bx d
bx c
bx b
bx a
bx `
bx _
bx ^
bx ]
bx \
bx Z
bx Y
bx X
bx W
bx V
bx U
bx S
bx R
bx Q
bx P
bx O
bx N
bx D
bx C
bx B
bx A
bx @
bx ?
bx >
bx =
bx <
bx ;
bx :
x9
x8
bx 7
bx 6
bx 5
bx 4
bx 3
bx 2
x1
x0
x/
bx .
bx -
bx ,
bx +
bx *
bx )
x(
bx '
bx &
bx %
bx $
x#
1"
0!
$end
#5000
b101010 %
b101010 d
0#
b101010 :
b101010 A
b101010 Q
b1010 >
b101010 <
b101010 =
b101010 4
b101010 `
b0 )
b0 S
b0 e
b0 *
b0 @
b0 f
b0 3
b0 O
b0 ^
b0 ;
b0 ?
b0 N
b0 $
b0 P
1(
19
00
0/
08
01
b1 5
b1 C
b1010 &
b1010 b
b0 '
b0 a
b0 6
b0 B
b0 R
b1 +
b1 c
b10011 .
b10011 D
b10101000000000000010010011 2
b10101000000000000010010011 X
b10101000000000000010010011 Y
b10101000000000000010010011 _
b100 ,
b100 V
b100 \
b0 -
b0 W
b0 Z
b0 ]
1!
#10000
0!
0"
#15000
1#
b0 %
b0 d
b0 :
b0 A
b0 Q
b0 >
b0 <
b0 =
b101010 )
b101010 S
b101010 e
b1 3
b1 O
b1 ^
1/
0(
19
b0 4
b0 `
b0 5
b0 C
b1 &
b1 b
b10 6
b10 B
b10 R
b0 +
b0 c
b100011 .
b100011 D
b100000010000000100011 2
b100000010000000100011 X
b100000010000000100011 Y
b100000010000000100011 _
b1000 ,
b1000 V
b1000 \
b100 -
b100 W
b100 Z
b100 ]
1!
#20000
0!
#25000
1#
b0 :
b0 A
b0 Q
b0 >
b101010 %
b101010 d
b0 <
b0 =
b0 )
b0 S
b0 e
b1 $
b1 P
10
1(
b0 3
b0 O
b0 ^
19
0/
b0 4
b0 `
b0 &
b0 b
b10 +
b10 c
b11 .
b11 D
b10000100000011 2
b10000100000011 X
b10000100000011 Y
b10000100000011 _
b101010 7
b101010 U
b1100 ,
b1100 V
b1100 \
b1000 -
b1000 W
b1000 Z
b1000 ]
1!
#30000
0!
#35000
b0 %
b0 d
b0 $
b0 P
1(
19
00
b0 6
b0 B
b0 R
b0 +
b0 c
b10011 .
b10011 D
b10011 2
b10011 X
b10011 Y
b10011 _
b10000 ,
b10000 V
b10000 \
b1100 -
b1100 W
b1100 Z
b1100 ]
1!
#40000
0!
#45000
bx %
bx d
bx >
x#
bx :
bx A
bx Q
bx <
bx =
bx )
bx S
bx e
bx *
bx @
bx f
b0 7
b0 U
0(
09
bx 4
bx `
bx 5
bx C
bx &
bx b
bx '
bx a
bx 6
bx B
bx R
bx +
bx c
bx .
bx D
bx 2
bx X
bx Y
bx _
b10100 ,
b10100 V
b10100 \
b10000 -
b10000 W
b10000 Z
b10000 ]
1!
#50000
0!
#55000
b11000 ,
b11000 V
b11000 \
b10100 -
b10100 W
b10100 Z
b10100 ]
1!
#60000
0!
#65000
b11100 ,
b11100 V
b11100 \
b11000 -
b11000 W
b11000 Z
b11000 ]
1!
