RTL/branch_unit.v

module branch_unit (
    input  [ 2:0] funct3,
    input         zero,        // ALU: rs1 == rs2
    input         alu_lt,      // ALU: rs1 < rs2 (signed)
    input         alu_ltu,     // ALU: rs1 < rs2 (unsigned)
    input  [31:0] pc,
    input  [31:0] b_imm,       // sign-extended B-immediate
    output reg    branch_taken,
    output [31:0] branch_target
);
assign branch_target = pc + b_imm;

always @(*) begin
    case (funct3)
        3'b000: branch_taken =  zero;         // BEQ
        3'b001: branch_taken = ~zero;         // BNE
        3'b100: branch_taken =  alu_lt;       // BLT
        3'b101: branch_taken = ~alu_lt;       // BGE
        3'b110: branch_taken =  alu_ltu;      // BLTU
         3'b111: branch_taken = ~alu_ltu;      // BGEU
        default: branch_taken = 1'b0;
        endcase
end
endmodule

RTL/dmem.v
module dmem#(parameter depth=256)(
    input clk,
    input we,
    input [31:0]addr,
    input [31:0]wdata,
    input [2:0]funct3,
    output reg [31:0]rdata
);

reg [7:0] mem[0:(depth*4)-1];

always @(posedge clk)
begin
    if (we)begin
        case(funct3)
        3'b000:begin
            mem[addr]<=wdata[7:0];
        end
        3'b001:begin
            mem[addr]<=wdata[7:0];
            mem[addr+1]<=wdata[15:8];
        end
        3'b010:begin
            mem[addr]<=wdata[7:0];
            mem[addr+1]<=wdata[15:8];
            mem[addr+2]<=wdata[23:16];
            mem[addr+3]<=wdata[31:24];
        end
        default: ;
        endcase
    end
end
always @(*)
begin
    case(funct3)
    3'b000:begin
        rdata={{24{mem[addr][7]}},mem[addr]};
    end
    3'b001:begin
        rdata={{16{mem[addr+1][7]}},mem[addr+1],mem[addr]};
    end
    3'b010:begin
        rdata={mem[addr+3],mem[addr+2],mem[addr+1],mem[addr]};
    end
    3'b100:begin
        rdata={24'b0,mem[addr]};
    end
    3'b101:begin
        rdata={16'b0,mem[addr+1],mem[addr]};
    end
    default:rdata=32'b0;
    endcase
end
endmodule

RTL/alu.v
module alu (
    input  [31:0] a,
    input  [31:0] b,
    input  [3:0] aluop,
    output reg [31:0] result,
    output wire zero,
    output wire alu_lt,
    output wire alu_ltu
);
wire [4:0]shiftamt =b[4:0];
assign alu_lt  = ($signed(a) < $signed(b));
assign alu_ltu = (a < b);
always@(*)begin
    case (aluop)
    4'b0000: result =a+b;
    4'b0001: result =a-b;
    4'b0010: result =a&b;
    4'b0011: result =a|b;
    4'b0100: result =a^b;
    4'b0101: result =($signed(a)<$signed(b))?32'd1:32'd0;
    4'b0110: result =(a<b);
    4'b0111: result =a<<shiftamt;
    4'b1000: result =a>>shiftamt;
    4'b1001: result =$signed(a)>>>shiftamt;
    default: result= 32'b0;
    endcase
end

assign zero =(result==32'd0);
endmodule

RTL/immgen.v
module immgen(
    input [31:0] instr,
    input [2:0] imm_sel,
    output reg [31:0] immediate
);

always @(*) begin
    case (imm_sel)
       3'b000: immediate= {{20{instr[31]}},instr[31:20]};
       3'b001: immediate= {{20{instr[31]}},instr[31:25],instr[11:7]};
       3'b010: immediate= {{19{instr[31]}}, instr[31], instr[7],instr[30:25], instr[11:8], 1'b0};
       3'b011: immediate = {instr[31:12], 12'b0};
       3'b100: immediate = {{11{instr[31]}}, instr[31], instr[19:12],instr[20], instr[30:21], 1'b0};
    endcase
end
endmodule

RTL/regfile.v
module regfile(
    input clk,
    input wen,
    input [4:0] waddr,
    input [31:0] wdata,
    input [4:0] raddr1,
    input [4:0] raddr2,
    output [31:0] rdata1,
    output [31:0] rdata2
);
reg [31:0] regs[0:31];
integer i;
 initial for(i=0;i<32;i++) regs[i]=32'b0;

always @(posedge clk)
if (wen && waddr !=5'b0) regs[waddr]<= wdata;

assign rdata1= (raddr1==0)? 32'b0 : regs[raddr1];
assign rdata2= (raddr2==0)? 32'b0 : regs[raddr2];
endmodule

RTL/control.v
module control(
    input  [6:0]opcode,
    input  [2:0]funct3,
    input  [6:0]funct7,
    output reg reg_write,
    output reg alu_src,
    output reg mem_read,
    output reg mem_write,
    output reg branch,
    output reg jump,
    output reg [1:0]wb_sel,
    output reg [3:0]alu_op,
    output reg [2:0]imm_sel
);

localparam R = 7'b0110011;
localparam I = 7'b0010011;
localparam LOAD = 7'b0000011;
localparam STORE = 7'b0100011;
localparam BR = 7'b1100011;
localparam JAL = 7'b1101111;
localparam JALR= 7'b1100111;  
localparam LUI = 7'b0110111;  
localparam AUIP= 7'b0010111;  


always @(*) begin
    {reg_write,alu_src,mem_read,mem_write,branch,jump}=6'b0;
    wb_sel=2'b00; alu_op=4'b0000; imm_sel=3'b000;
    //safe assignment
    case (opcode)
        R: begin
            reg_write=1; alu_src=0; wb_sel=2'b00;
            case({funct7[5],funct3})
                4'b0000: alu_op=4'b0000; // ADD
                4'b1000: alu_op=4'b0001; // SUB
                4'b0111: alu_op=4'b0010; // AND
                4'b0110: alu_op=4'b0011; // OR
                4'b0100: alu_op=4'b0100; // XOR
                4'b0010: alu_op=4'b0101; // SLT
                4'b0011: alu_op=4'b0110; // SLTU
                4'b0001: alu_op=4'b0111; // SLL
                4'b0101: alu_op=4'b1000; // SRL
                4'b1101: alu_op=4'b1001; // SRA
                default: alu_op=4'b0000;
            endcase
        end

        I:  begin 
            reg_write=1; alu_src=1; wb_sel=2'b00; imm_sel=3'b000;
            case(funct3)
                3'h0: alu_op=4'b0000; // ADDI
                3'h7: alu_op=4'b0010; // ANDI
                3'h6: alu_op=4'b0011; // ORI
                3'h4: alu_op=4'b0100; // XORI
                3'h2: alu_op=4'b0101; // SLTI
                3'h3: alu_op=4'b0110; // SLTIU
                3'h1: alu_op=4'b0111; // SLLI
                3'h5: alu_op=(funct7[5])?4'b1001:4'b1000; // SRAI/SRLI
                default: alu_op=4'b0000;
            endcase
        end

        LOAD: begin 
            reg_write=1; alu_src=1; mem_read=1; wb_sel=2'b01; imm_sel=3'b000; alu_op=4'b0000;
        end

        STORE: begin 
            alu_src=1; mem_write=1; imm_sel=3'b001; alu_op=4'b0000;
        end

        BR: begin
            branch = 1; alu_src = 0; imm_sel = 3'b010; alu_op = 4'b0001; 
end
        JAL:  begin 
            reg_write=1; jump=1; wb_sel=2'b10; imm_sel=3'b100;
        end
            
        JALR: begin 
                reg_write=1; alu_src=1; jump=1; wb_sel=2'b10; imm_sel=3'b000; alu_op=4'b0000; 
        end
                
        LUI:  begin
                 reg_write=1; wb_sel=2'b11; imm_sel=3'b011; 
        end
                 
        AUIP: begin
                 reg_write=1; alu_src=1; wb_sel=2'b00; imm_sel=3'b011; alu_op=4'b0000; 
        end

        default: ;
    endcase
end
endmodule

RTL/imem.v
module imem #(parameter depth = 256)(addr,instr);
input [31:0]addr;
output [31:0] instr;
reg [31:0] mem[0:depth-1];
//initial $readmemh("program1.hex",mem);
assign instr=mem[addr[31:2]];
endmodule

pc.v
module program_counter(clk,rst,pc_next,pc);
input clk,rst;
input wire [31:0]pc_next;
output reg [31:0]pc;
always @(posedge clk) begin
    if (rst) pc=32'h00000000;
    else pc<=pc_next;
end
endmodule

RTL/instfetch.v
module instfetch(clk,rst,pc_next,pc,instr);
input clk,rst;
input [31:0]pc_next;
output [31:0]instr;
output [31:0] pc;//only for tb purpose this is output,otherwire internally used by imem 
program_counter pcconnect(clk,rst,pc_next,pc);
imem imemconnect(pc,instr);
endmodule

RTL/RISCVCORE.v
module RISCVCORE(
    input clk,rst
);
wire [31:0] pc, pc_next, instr;

instfetch if0(clk,rst,pc_next,pc,instr);

//decoding
wire[6:0] opcode =instr[6:0];
wire [4:0] rd =instr[11:7];
wire [2:0] funct3 =instr[14:12];
wire [4:0] rs1 = instr[19:15];
wire [4:0] rs2= instr[24:20];
wire [6:0] funct7=instr[31:25];

//control unit
wire reg_write, alu_src;
wire [3:0] alu_op;
wire [2:0] imm_sel;
wire mem_read, mem_write, branch, jump;
wire [1:0] wb_sel;
control ctrl(
    .opcode(opcode),
    .funct3(funct3),
    .funct7(funct7),
    .reg_write(reg_write),
    .alu_src(alu_src),
    .mem_read(mem_read),
    .mem_write(mem_write),
    .branch(branch),
    .jump(jump),
    .wb_sel(wb_sel),
    .alu_op(alu_op),
    .imm_sel(imm_sel)
);

//regfile
wire [31:0] rdata1,rdata2,wb_data;
regfile rf (
    .clk(clk),
    .wen(reg_write),
    .waddr(rd),
    .wdata(wb_data),
    .raddr1(rs1),
    .raddr2(rs2),
    .rdata1(rdata1),
    .rdata2(rdata2)
);

//immediate gen
wire [31:0] imm;
immgen ig0(
    .instr(instr),
    .imm_sel(imm_sel),
    .immediate(imm)
);

//ALU source mux
wire [31:0] alu_b   = alu_src ? imm : rdata2;
wire alu_src_a = (opcode == 7'b0010111);
wire [31:0] alu_a = alu_src_a ? pc : rdata1;
wire [31:0]alu_result;
wire zero,alu_lt, alu_ltu;
alu alu0(
    .a(alu_a),
    .b(alu_b),
    .aluop(alu_op),
    .result(alu_result),
    .zero(zero),
    .alu_lt(alu_lt),
    .alu_ltu(alu_ltu)
);

//Data Memory
wire [31:0]dmem_rdata;
dmem dmem0(
    .clk(clk),
    .we(mem_write),
    .addr(alu_result),
    .wdata(rdata2),
    .funct3(funct3),
    .rdata(dmem_rdata)
);
//Branch unit
wire branch_taken;
wire [31:0] branch_target;

branch_unit bu0 (
    .funct3(funct3),
    .zero(zero),
    .alu_lt(alu_lt),
    .alu_ltu(alu_ltu),
    .pc(pc),
    .b_imm(imm),
    .branch_taken(branch_taken),
    .branch_target(branch_target)
);
// PC Update Logic
wire pc_sel_branch = branch & branch_taken;
wire [31:0] jal_target  = pc + imm;
wire [31:0] jalr_target = {alu_result[31:1], 1'b0};

assign pc_next = (opcode == 7'b1100111) ? jalr_target :      // JALR
                 (jump)                 ? jal_target :       // JAL
                 (pc_sel_branch)        ? branch_target :    // Taken Branch
                                          (pc + 32'd4);      // Default PC + 4
//write back 
assign wb_data = (wb_sel == 2'b00) ? alu_result :
                 (wb_sel == 2'b01) ? dmem_rdata :
                 (wb_sel == 2'b10) ? (pc + 32'd4) :
                 (wb_sel == 2'b11) ? imm :
                                     32'b0;
endmodule

Testbenches/TheTestbench.v
// tb_riscv_core.v — Converted for RISCVCORE
`timescale 1ns/1ps

module tb_riscv_core;
    reg clk = 0, rst = 1;
    always #5 clk = ~clk; // 100 MHz

    // Instantiation using your module name RISCVCORE
    RISCVCORE dut (
        .clk(clk),
        .rst(rst)
    );

    integer i;
    reg [31:0] result;

    initial begin
        // Path matches instfetch -> imemconnect -> mem
        $readmemh("program.hex", dut.if0.imemconnect.mem);

        $dumpfile("tb_riscv_core.vcd");
        $dumpvars(0, tb_riscv_core);

        // Release reset after 2 cycles
        repeat(2) @(posedge clk);
        rst = 0;

        // Run for 50 cycles to allow loop completion
        repeat(50) @(posedge clk);
        #1;

        // Check: memory address 0 should contain 15 (sum 1..5)
        result = {dut.dmem0.mem[3], dut.dmem0.mem[2],
                  dut.dmem0.mem[1], dut.dmem0.mem[0]};

        if (result === 32'd15)
            $display("PASS: sum(1..5) = %0d stored at mem[0]", result);
        else
            $display("FAIL: mem[0] = %0d (expected 15)", result);

        // Dump first 8 registers
        $display("--- Register File Snapshot ---");
        for (i = 0; i < 8; i = i + 1)
            $display("  x%0d = %0d", i, dut.rf.regs[i]);

        $finish;
    end
endmodule

VCD/tb_riscv_core.vcd
$date
	Fri Sep 25 23:59:57 2026
$end
$version
	Icarus Verilog
$end
$timescale
	1ps
$end
$scope module tb_riscv_core $end
$var reg 1 ! clk $end
$var reg 32 " result [31:0] $end
$var reg 1 # rst $end
$var integer 32 $ i [31:0] $end
$scope module dut $end
$var wire 1 ! clk $end
$var wire 1 % pc_sel_branch $end
$var wire 1 # rst $end
$var wire 1 & zero $end
$var wire 2 ' wb_sel [1:0] $end
$var wire 32 ( wb_data [31:0] $end
$var wire 5 ) rs2 [4:0] $end
$var wire 5 * rs1 [4:0] $end
$var wire 1 + reg_write $end
$var wire 32 , rdata2 [31:0] $end
$var wire 32 - rdata1 [31:0] $end
$var wire 5 . rd [4:0] $end
$var wire 32 / pc_next [31:0] $end
$var wire 32 0 pc [31:0] $end
$var wire 7 1 opcode [6:0] $end
$var wire 1 2 mem_write $end
$var wire 1 3 mem_read $end
$var wire 1 4 jump $end
$var wire 32 5 jalr_target [31:0] $end
$var wire 32 6 jal_target [31:0] $end
$var wire 32 7 instr [31:0] $end
$var wire 3 8 imm_sel [2:0] $end
$var wire 32 9 imm [31:0] $end
$var wire 7 : funct7 [6:0] $end
$var wire 3 ; funct3 [2:0] $end
$var wire 32 < dmem_rdata [31:0] $end
$var wire 32 = branch_target [31:0] $end
$var wire 1 > branch_taken $end
$var wire 1 ? branch $end
$var wire 1 @ alu_src_a $end
$var wire 1 A alu_src $end
$var wire 32 B alu_result [31:0] $end
$var wire 4 C alu_op [3:0] $end
$var wire 1 D alu_ltu $end
$var wire 1 E alu_lt $end
$var wire 32 F alu_b [31:0] $end
$var wire 32 G alu_a [31:0] $end
$scope module alu0 $end
$var wire 32 H a [31:0] $end
$var wire 32 I b [31:0] $end
$var wire 1 & zero $end
$var wire 5 J shiftamt [4:0] $end
$var wire 4 K aluop [3:0] $end
$var wire 1 D alu_ltu $end
$var wire 1 E alu_lt $end
$var reg 32 L result [31:0] $end
$upscope $end
$scope module bu0 $end
$var wire 1 E alu_lt $end
$var wire 1 D alu_ltu $end
$var wire 3 M funct3 [2:0] $end
$var wire 1 & zero $end
$var wire 32 N pc [31:0] $end
$var wire 32 O branch_target [31:0] $end
$var wire 32 P b_imm [31:0] $end
$var reg 1 > branch_taken $end
$upscope $end
$scope module ctrl $end
$var wire 3 Q funct3 [2:0] $end
$var wire 7 R funct7 [6:0] $end
$var wire 7 S opcode [6:0] $end
$var parameter 7 T AUIP $end
$var parameter 7 U BR $end
$var parameter 7 V I $end
$var parameter 7 W JAL $end
$var parameter 7 X JALR $end
$var parameter 7 Y LOAD $end
$var parameter 7 Z LUI $end
$var parameter 7 [ R $end
$var parameter 7 \ STORE $end
$var reg 4 ] alu_op [3:0] $end
$var reg 1 A alu_src $end
$var reg 1 ? branch $end
$var reg 3 ^ imm_sel [2:0] $end
$var reg 1 4 jump $end
$var reg 1 3 mem_read $end
$var reg 1 2 mem_write $end
$var reg 1 + reg_write $end
$var reg 2 _ wb_sel [1:0] $end
$upscope $end
$scope module dmem0 $end
$var wire 32 ` addr [31:0] $end
$var wire 1 ! clk $end
$var wire 3 a funct3 [2:0] $end
$var wire 1 2 we $end
$var wire 32 b wdata [31:0] $end
$var parameter 32 c depth $end
$var reg 32 d rdata [31:0] $end
$upscope $end
$scope module if0 $end
$var wire 1 ! clk $end
$var wire 32 e pc_next [31:0] $end
$var wire 1 # rst $end
$var wire 32 f pc [31:0] $end
$var wire 32 g instr [31:0] $end
$scope module imemconnect $end
$var wire 32 h instr [31:0] $end
$var wire 32 i addr [31:0] $end
$var parameter 32 j depth $end
$upscope $end
$scope module pcconnect $end
$var wire 1 ! clk $end
$var wire 32 k pc_next [31:0] $end
$var wire 1 # rst $end
$var reg 32 l pc [31:0] $end
$upscope $end
$upscope $end
$scope module ig0 $end
$var wire 3 m imm_sel [2:0] $end
$var wire 32 n instr [31:0] $end
$var reg 32 o immediate [31:0] $end
$upscope $end
$scope module rf $end
$var wire 1 ! clk $end
$var wire 5 p raddr1 [4:0] $end
$var wire 5 q raddr2 [4:0] $end
$var wire 5 r waddr [4:0] $end
$var wire 32 s wdata [31:0] $end
$var wire 1 + wen $end
$var wire 32 t rdata2 [31:0] $end
$var wire 32 u rdata1 [31:0] $end
$var integer 32 v i [31:0] $end
$upscope $end
$upscope $end
$upscope $end
$enddefinitions $end
$comment Show the parameter values. $end
$dumpall
b100000000 j
b100000000 c
b100011 \
b110011 [
b110111 Z
b11 Y
b1100111 X
b1101111 W
b10011 V
b1100011 U
b10111 T
$end
#0
$dumpvars
b100000 v
bx u
bx t
bx s
bx r
bx q
bx p
bx o
bx n
bx m
bx l
bx k
bx i
bx h
bx g
bx f
bx e
bx d
bx b
bx a
bx `
bx _
bx ^
bx ]
bx S
bx R
bx Q
bx P
bx O
bx N
bx M
bx L
bx K
bx J
bx I
bx H
bx G
bx F
xE
xD
bx C
bx B
xA
x@
x?
x>
bx =
bx <
bx ;
bx :
bx 9
bx 8
bx 7
bx 6
bx0 5
x4
x3
x2
bx 1
bx 0
bx /
bx .
bx -
bx ,
x+
bx *
bx )
bx (
bx '
x&
x%
bx $
1#
bx "
0!
$end
#5000
b100 /
b100 e
b100 k
b1 (
b1 s
b0 5
b1 J
0>
0&
b1 B
b1 L
b1 `
1E
1D
b1 F
b1 I
b0 G
b0 H
b1 =
b1 O
b1 6
b1 9
b1 P
b1 o
0%
b0 ,
b0 b
b0 t
b0 -
b0 u
b0 8
b0 ^
b0 m
b0 C
b0 K
b0 ]
b0 '
b0 _
1+
1A
03
02
0?
04
b0 :
b0 R
b1 )
b1 q
b0 *
b0 p
b0 ;
b0 M
b0 Q
b0 a
b1 .
b1 r
0@
b10011 1
b10011 S
b100000000000010010011 7
b100000000000010010011 g
b100000000000010010011 h
b100000000000010010011 n
b0 0
b0 N
b0 f
b0 i
b0 l
1!
#10000
0!
#15000
b1 ,
b1 b
b1 t
0#
1!
#20000
0!
#25000
1>
b0 (
b0 s
1&
b0 B
b0 L
b0 `
b0 J
0E
0D
b0 F
b0 I
b0 ,
b0 b
b0 t
b1000 /
b1000 e
b1000 k
b0 9
b0 P
b0 o
b0 )
b0 q
b10 .
b10 r
b100010011 7
b100010011 g
b100010011 h
b100010011 n
b100 =
b100 O
b100 6
b100 0
b100 N
b100 f
b100 i
b100 l
1!
#30000
0!
#35000
0>
b110 (
b110 s
b110 5
0&
b110 B
b110 L
b110 `
b110 J
1E
1D
b110 F
b110 I
b1100 /
b1100 e
b1100 k
b110 9
b110 P
b110 o
b110 )
b110 q
b11 .
b11 r
b11000000000000110010011 7
b11000000000000110010011 g
b11000000000000110010011 h
b11000000000000110010011 n
b1110 =
b1110 O
b1110 6
b1000 0
b1000 N
b1000 f
b1000 i
b1000 l
1!
#40000
0!
#45000
b11111111111111111111111111111011 (
b11111111111111111111111111111011 s
b11111111111111111111111111111010 5
b1 G
b1 H
b11111111111111111111111111111011 B
b11111111111111111111111111111011 L
b11111111111111111111111111111011 `
b110 ,
b110 b
b110 t
b1 -
b1 u
b0xxxxxxxxxxxxxxxx <
b0xxxxxxxxxxxxxxxx d
b1 C
b1 K
b1 ]
b10 8
b10 ^
b10 m
1?
0+
0A
b10000 /
b10000 e
b10000 k
b10000 9
b10000 P
b10000 o
b11 )
b11 q
b1 *
b1 p
b101 ;
b101 M
b101 Q
b101 a
b10000 .
b10000 r
b1100011 1
b1100011 S
b1100001101100001100011 7
b1100001101100001100011 g
b1100001101100001100011 h
b1100001101100001100011 n
b11100 =
b11100 O
b11100 6
b1100 0
b1100 N
b1100 f
b1100 i
b1100 l
1!
#50000
0!
#55000
b1 J
b1 (
b1 s
b0 5
b1 F
b1 I
b0 G
b0 H
b1 B
b1 L
b1 `
b1 ,
b1 b
b1 t
b0 -
b0 u
bx <
bx d
1+
b0 8
b0 ^
b0 m
b0 C
b0 K
b0 ]
0?
b10100 /
b10100 e
b10100 k
b1 9
b1 P
b1 o
b1 )
b1 q
b10 *
b10 p
b0 ;
b0 M
b0 Q
b0 a
b10 .
b10 r
b110011 1
b110011 S
b100010000000100110011 7
b100010000000100110011 g
b100010000000100110011 h
b100010000000100110011 n
b10001 =
b10001 O
b10001 6
b10000 0
b10000 N
b10000 f
b10000 i
b10000 l
1!
#60000
0!
#65000
b10 (
b10 s
b10 5
1A
1+
b11000 /
b11000 e
b11000 k
b10 B
b10 L
b10 `
b1 *
b1 p
b1 .
b1 r
b10011 1
b10011 S
0E
0D
b1 G
b1 H
b100001000000010010011 7
b100001000000010010011 g
b100001000000010010011 h
b100001000000010010011 n
b1 -
b1 u
b10101 =
b10101 O
b10101 6
b10100 0
b10100 N
b10100 f
b10100 i
b10100 l
1!
#70000
0!
#75000
b0 5
1&
b0 B
b0 L
b0 `
b0 J
b11100 (
b11100 s
b0 F
b0 I
1>
b0 <
b0 d
b100 8
b100 ^
b100 m
b10 '
b10 _
14
1+
0A
b1100 /
b1100 e
b1100 k
b0 G
b0 H
b11111111111111111111111111110100 9
b11111111111111111111111111110100 P
b11111111111111111111111111110100 o
b1111111 :
b1111111 R
b10101 )
b10101 q
b11111 *
b11111 p
b111 ;
b111 M
b111 Q
b111 a
b0 .
b0 r
b1101111 1
b1101111 S
b0 -
b0 u
b0 ,
b0 b
b0 t
b11111111010111111111000001101111 7
b11111111010111111111000001101111 g
b11111111010111111111000001101111 h
b11111111010111111111000001101111 n
b1100 =
b1100 O
b1100 6
b11000 0
b11000 N
b11000 f
b11000 i
b11000 l
1!
#80000
0!
#85000
b11111111111111111111111111111100 5
b110 J
0>
0&
b11111111111111111111111111111100 B
b11111111111111111111111111111100 L
b11111111111111111111111111111100 `
1E
1D
b110 F
b110 I
b10 G
b10 H
0%
b110 ,
b110 b
b110 t
b10 -
b10 u
b0xxxxxxxxxxxxxxxx <
b0xxxxxxxxxxxxxxxx d
b1 C
b1 K
b1 ]
1?
b10 8
b10 ^
b10 m
b0 '
b0 _
0+
04
b11111111111111111111111111111100 (
b11111111111111111111111111111100 s
b10000 9
b10000 P
b10000 o
b0 :
b0 R
b11 )
b11 q
b1 *
b1 p
b101 ;
b101 M
b101 Q
b101 a
b10000 .
b10000 r
b1100011 1
b1100011 S
b10000 /
b10000 e
b10000 k
b1100001101100001100011 7
b1100001101100001100011 g
b1100001101100001100011 h
b1100001101100001100011 n
b11100 =
b11100 O
b11100 6
b1100 0
b1100 N
b1100 f
b1100 i
b1100 l
1!
#90000
0!
#95000
b10 J
b11 (
b11 s
b10 5
b10 F
b10 I
b1 G
b1 H
b11 B
b11 L
b11 `
b10 ,
b10 b
b10 t
b1 -
b1 u
bx <
bx d
1+
b0 8
b0 ^
b0 m
b0 C
b0 K
b0 ]
0?
b10100 /
b10100 e
b10100 k
b1 9
b1 P
b1 o
b1 )
b1 q
b10 *
b10 p
b0 ;
b0 M
b0 Q
b0 a
b10 .
b10 r
b110011 1
b110011 S
b100010000000100110011 7
b100010000000100110011 g
b100010000000100110011 h
b100010000000100110011 n
b10001 =
b10001 O
b10001 6
b10000 0
b10000 N
b10000 f
b10000 i
b10000 l
1!
#100000
0!
#105000
b1 J
b1 F
b1 I
b11 (
b11 s
b10 5
1A
1+
b11000 /
b11000 e
b11000 k
b11 B
b11 L
b11 `
b1 *
b1 p
b1 .
b1 r
b10011 1
b10011 S
0E
0D
b10 G
b10 H
b100001000000010010011 7
b100001000000010010011 g
b100001000000010010011 h
b100001000000010010011 n
b10 -
b10 u
b10101 =
b10101 O
b10101 6
b10100 0
b10100 N
b10100 f
b10100 i
b10100 l
1!
#110000
0!
#115000
b0 5
1&
b0 B
b0 L
b0 `
b0 J
b11100 (
b11100 s
b0 F
b0 I
1>
b0 <
b0 d
b100 8
b100 ^
b100 m
b10 '
b10 _
14
1+
0A
b1100 /
b1100 e
b1100 k
b0 G
b0 H
b11111111111111111111111111110100 9
b11111111111111111111111111110100 P
b11111111111111111111111111110100 o
b1111111 :
b1111111 R
b10101 )
b10101 q
b11111 *
b11111 p
b111 ;
b111 M
b111 Q
b111 a
b0 .
b0 r
b1101111 1
b1101111 S
b0 -
b0 u
b0 ,
b0 b
b0 t
b11111111010111111111000001101111 7
b11111111010111111111000001101111 g
b11111111010111111111000001101111 h
b11111111010111111111000001101111 n
b1100 =
b1100 O
b1100 6
b11000 0
b11000 N
b11000 f
b11000 i
b11000 l
1!
#120000
0!
#125000
b11111111111111111111111111111100 5
b110 J
0>
0&
b11111111111111111111111111111101 B
b11111111111111111111111111111101 L
b11111111111111111111111111111101 `
1E
1D
b110 F
b110 I
b11 G
b11 H
0%
b110 ,
b110 b
b110 t
b11 -
b11 u
b0xxxxxxxxxxxxxxxx <
b0xxxxxxxxxxxxxxxx d
b1 C
b1 K
b1 ]
1?
b10 8
b10 ^
b10 m
b0 '
b0 _
0+
04
b11111111111111111111111111111101 (
b11111111111111111111111111111101 s
b10000 9
b10000 P
b10000 o
b0 :
b0 R
b11 )
b11 q
b1 *
b1 p
b101 ;
b101 M
b101 Q
b101 a
b10000 .
b10000 r
b1100011 1
b1100011 S
b10000 /
b10000 e
b10000 k
b1100001101100001100011 7
b1100001101100001100011 g
b1100001101100001100011 h
b1100001101100001100011 n
b11100 =
b11100 O
b11100 6
b1100 0
b1100 N
b1100 f
b1100 i
b1100 l
1!
#130000
0!
#135000
b11 J
b110 (
b110 s
b110 5
0E
0D
b11 F
b11 I
b110 B
b110 L
b110 `
b11 ,
b11 b
b11 t
bx <
bx d
1+
b0 8
b0 ^
b0 m
b0 C
b0 K
b0 ]
0?
b10100 /
b10100 e
b10100 k
b1 9
b1 P
b1 o
b1 )
b1 q
b10 *
b10 p
b0 ;
b0 M
b0 Q
b0 a
b10 .
b10 r
b110011 1
b110011 S
b100010000000100110011 7
b100010000000100110011 g
b100010000000100110011 h
b100010000000100110011 n
b10001 =
b10001 O
b10001 6
b10000 0
b10000 N
b10000 f
b10000 i
b10000 l
1!
#140000
0!
#145000
b1 J
b1 F
b1 I
b100 (
b100 s
b100 5
1A
1+
b11000 /
b11000 e
b11000 k
b100 B
b100 L
b100 `
b1 *
b1 p
b1 .
b1 r
b10011 1
b10011 S
b11 G
b11 H
b100001000000010010011 7
b100001000000010010011 g
b100001000000010010011 h
b100001000000010010011 n
b11 -
b11 u
b10101 =
b10101 O
b10101 6
b10100 0
b10100 N
b10100 f
b10100 i
b10100 l
1!
#150000
0!
#155000
b0 5
1&
b0 B
b0 L
b0 `
b0 J
b11100 (
b11100 s
b0 F
b0 I
1>
b0 <
b0 d
b100 8
b100 ^
b100 m
b10 '
b10 _
14
1+
0A
b1100 /
b1100 e
b1100 k
b0 G
b0 H
b11111111111111111111111111110100 9
b11111111111111111111111111110100 P
b11111111111111111111111111110100 o
b1111111 :
b1111111 R
b10101 )
b10101 q
b11111 *
b11111 p
b111 ;
b111 M
b111 Q
b111 a
b0 .
b0 r
b1101111 1
b1101111 S
b0 -
b0 u
b0 ,
b0 b
b0 t
b11111111010111111111000001101111 7
b11111111010111111111000001101111 g
b11111111010111111111000001101111 h
b11111111010111111111000001101111 n
b1100 =
b1100 O
b1100 6
b11000 0
b11000 N
b11000 f
b11000 i
b11000 l
1!
#160000
0!
#165000
b11111111111111111111111111111110 5
b110 J
0>
0&
b11111111111111111111111111111110 B
b11111111111111111111111111111110 L
b11111111111111111111111111111110 `
1E
1D
b110 F
b110 I
b100 G
b100 H
0%
b110 ,
b110 b
b110 t
b100 -
b100 u
b0xxxxxxxxxxxxxxxx <
b0xxxxxxxxxxxxxxxx d
b1 C
b1 K
b1 ]
1?
b10 8
b10 ^
b10 m
b0 '
b0 _
0+
04
b11111111111111111111111111111110 (
b11111111111111111111111111111110 s
b10000 9
b10000 P
b10000 o
b0 :
b0 R
b11 )
b11 q
b1 *
b1 p
b101 ;
b101 M
b101 Q
b101 a
b10000 .
b10000 r
b1100011 1
b1100011 S
b10000 /
b10000 e
b10000 k
b1100001101100001100011 7
b1100001101100001100011 g
b1100001101100001100011 h
b1100001101100001100011 n
b11100 =
b11100 O
b11100 6
b1100 0
b1100 N
b1100 f
b1100 i
b1100 l
1!
#170000
0!
#175000
b100 J
b1010 (
b1010 s
b1010 5
b100 F
b100 I
0E
0D
b110 G
b110 H
b1010 B
b1010 L
b1010 `
b100 ,
b100 b
b100 t
b110 -
b110 u
bx <
bx d
1+
b0 8
b0 ^
b0 m
b0 C
b0 K
b0 ]
0?
b10100 /
b10100 e
b10100 k
b1 9
b1 P
b1 o
b1 )
b1 q
b10 *
b10 p
b0 ;
b0 M
b0 Q
b0 a
b10 .
b10 r
b110011 1
b110011 S
b100010000000100110011 7
b100010000000100110011 g
b100010000000100110011 h
b100010000000100110011 n
b10001 =
b10001 O
b10001 6
b10000 0
b10000 N
b10000 f
b10000 i
b10000 l
1!
#180000
0!
#185000
b1 J
b1 F
b1 I
b101 (
b101 s
b100 5
1A
1+
b11000 /
b11000 e
b11000 k
b101 B
b101 L
b101 `
b1 *
b1 p
b1 .
b1 r
b10011 1
b10011 S
b100 G
b100 H
b100001000000010010011 7
b100001000000010010011 g
b100001000000010010011 h
b100001000000010010011 n
b100 -
b100 u
b10101 =
b10101 O
b10101 6
b10100 0
b10100 N
b10100 f
b10100 i
b10100 l
1!
#190000
0!
#195000
b0 5
1&
b0 B
b0 L
b0 `
b0 J
b11100 (
b11100 s
b0 F
b0 I
1>
b0 <
b0 d
b100 8
b100 ^
b100 m
b10 '
b10 _
14
1+
0A
b1100 /
b1100 e
b1100 k
b0 G
b0 H
b11111111111111111111111111110100 9
b11111111111111111111111111110100 P
b11111111111111111111111111110100 o
b1111111 :
b1111111 R
b10101 )
b10101 q
b11111 *
b11111 p
b111 ;
b111 M
b111 Q
b111 a
b0 .
b0 r
b1101111 1
b1101111 S
b0 -
b0 u
b0 ,
b0 b
b0 t
b11111111010111111111000001101111 7
b11111111010111111111000001101111 g
b11111111010111111111000001101111 h
b11111111010111111111000001101111 n
b1100 =
b1100 O
b1100 6
b11000 0
b11000 N
b11000 f
b11000 i
b11000 l
1!
#200000
0!
